rgbmatch.py
rgbmatch-0.0.1.dist-info/METADATA
rgbmatch-0.0.1.dist-info/WHEEL
rgbmatch-0.0.1.dist-info/top_level.txt
rgbmatch-0.0.1.dist-info/RECORD
