Metadata-Version: 2.1
Name: rgbmatch
Version: 0.0.1
Summary: Close RGB Colors
License: The Unlicense
Keywords: rgb
Classifier: Natural Language :: English
Classifier: Programming Language :: Python :: 3
Classifier: Topic :: Utilities
Classifier: Typing :: Typed
Requires-Python: >=3.7
Provides-Extra: tests
Requires-Dist: pytest ; extra == 'tests'
